{
  "formatVersion": "1.1",
  "component": {
    "group": "it.disi.unitn.ffmpeg",
    "module": "ffmpeg-java-id",
    "version": "1.1.22",
    "attributes": {
      "org.gradle.status": "release"
    }
  },
  "createdBy": {
    "gradle": {
      "version": "8.7"
    }
  },
  "variants": [
    {
      "name": "apiElements",
      "attributes": {
        "org.gradle.category": "library",
        "org.gradle.dependency.bundling": "external",
        "org.gradle.jvm.version": 21,
        "org.gradle.libraryelements": "jar",
        "org.gradle.usage": "java-api"
      },
      "files": [
        {
          "name": "ffmpeg-java-id-1.1.22.jar",
          "url": "ffmpeg-java-id-1.1.22.jar",
          "size": 129432,
          "sha512": "143fafc871f7527b48086d696ff851988a122f542f97ec7f8b1f582d028d760440f08039d6d4e2fc249d1ae21ea197aebde46372fb22271be85ef29eadc20ed3",
          "sha256": "5df33f1773ad42c35848c6c6efc9bc6eccfb49f5f9d5ac0616982ea104baefdf",
          "sha1": "e6453c1eff975ce6bcd1e1469b7c2bb6ad6826d9",
          "md5": "364ecb7f986619c88b0ce61b8219f16c"
        }
      ]
    },
    {
      "name": "runtimeElements",
      "attributes": {
        "org.gradle.category": "library",
        "org.gradle.dependency.bundling": "external",
        "org.gradle.jvm.version": 21,
        "org.gradle.libraryelements": "jar",
        "org.gradle.usage": "java-runtime"
      },
      "dependencies": [
        {
          "group": "org.jetbrains",
          "module": "annotations",
          "version": {
            "requires": "24.1.0"
          }
        },
        {
          "group": "com.google.cloud",
          "module": "libraries-bom",
          "version": {
            "requires": "26.39.0"
          },
          "attributes": {
            "org.gradle.category": "platform"
          },
          "endorseStrictVersions": true
        },
        {
          "group": "com.google.code.gson",
          "module": "gson",
          "version": {
            "requires": "2.11.0"
          }
        },
        {
          "group": "org.slf4j",
          "module": "slf4j-api",
          "version": {
            "requires": "2.0.13"
          }
        },
        {
          "group": "commons-io",
          "module": "commons-io",
          "version": {
            "requires": "2.16.1"
          }
        },
        {
          "group": "org.apache.commons",
          "module": "commons-lang3",
          "version": {
            "requires": "3.14.0"
          }
        },
        {
          "group": "org.apache.commons",
          "module": "commons-exec",
          "version": {
            "requires": "1.4.0"
          }
        },
        {
          "group": "org.owasp.encoder",
          "module": "encoder",
          "version": {
            "requires": "1.2.3"
          }
        }
      ],
      "files": [
        {
          "name": "ffmpeg-java-id-1.1.22.jar",
          "url": "ffmpeg-java-id-1.1.22.jar",
          "size": 129432,
          "sha512": "143fafc871f7527b48086d696ff851988a122f542f97ec7f8b1f582d028d760440f08039d6d4e2fc249d1ae21ea197aebde46372fb22271be85ef29eadc20ed3",
          "sha256": "5df33f1773ad42c35848c6c6efc9bc6eccfb49f5f9d5ac0616982ea104baefdf",
          "sha1": "e6453c1eff975ce6bcd1e1469b7c2bb6ad6826d9",
          "md5": "364ecb7f986619c88b0ce61b8219f16c"
        }
      ]
    },
    {
      "name": "javadocElements",
      "attributes": {
        "org.gradle.category": "documentation",
        "org.gradle.dependency.bundling": "external",
        "org.gradle.docstype": "javadoc",
        "org.gradle.usage": "java-runtime"
      },
      "files": [
        {
          "name": "ffmpeg-java-id-1.1.22-javadoc.jar",
          "url": "ffmpeg-java-id-1.1.22-javadoc.jar",
          "size": 389942,
          "sha512": "02c4aefd27ce580bf2f805b1457698cc2eebcf5dc186db6888ebde09ff2cdfd141671c143ff51f2f7e436fd11df5e0bbf06e412448af34aa8bda0817b3de49bb",
          "sha256": "d5af0a85071c9f6f5bf63c3901b10baee0e13236a8c52140f804683357ae15d3",
          "sha1": "4686678d3ddd5973474f7f2dc38aeae6a46782ac",
          "md5": "45937ded868bec371c654220a6b6febf"
        }
      ]
    },
    {
      "name": "sourcesElements",
      "attributes": {
        "org.gradle.category": "documentation",
        "org.gradle.dependency.bundling": "external",
        "org.gradle.docstype": "sources",
        "org.gradle.usage": "java-runtime"
      },
      "files": [
        {
          "name": "ffmpeg-java-id-1.1.22-sources.jar",
          "url": "ffmpeg-java-id-1.1.22-sources.jar",
          "size": 93158,
          "sha512": "19fab9aeb6514fbfd22dd2666cee2a70ba8a16907b15afd4017b64724aa40bcb4b117880b98608842426e52ee4195c78d896b63f99ebc5393a2288334bcc825e",
          "sha256": "819fb00c006aa4928eb06d556542ac2ba4b141b255cff5566a25399140b80ecb",
          "sha1": "d84a2d5d644c1f06232dcd397eb949bcfdf084de",
          "md5": "26cd8ce595955f9791b4bcfc943dc9e9"
        }
      ]
    }
  ]
}
