{
  "formatVersion": "1.1",
  "component": {
    "group": "it.disi.unitn.ffmpeg",
    "module": "ffmpeg-java-id",
    "version": "1.2.9-beta2.4",
    "attributes": {
      "org.gradle.status": "release"
    }
  },
  "createdBy": {
    "gradle": {
      "version": "8.10.2"
    }
  },
  "variants": [
    {
      "name": "apiElements",
      "attributes": {
        "org.gradle.category": "library",
        "org.gradle.dependency.bundling": "external",
        "org.gradle.jvm.version": 21,
        "org.gradle.libraryelements": "jar",
        "org.gradle.usage": "java-api"
      },
      "files": [
        {
          "name": "ffmpeg-java-id-1.2.9-beta2.4.jar",
          "url": "ffmpeg-java-id-1.2.9-beta2.4.jar",
          "size": 187450,
          "sha512": "9f20856a0b408743741ef346898f9fe1c57710e4c2dfc8d628aa3f897617ce38b31263e119841ae593259c6c6a9b2f099f38e8845e33c830b92f5a0b5e415d83",
          "sha256": "bb6d6224e115f19efbd47dd8ce7b3f99c6871a388218926cf1982021e53a7625",
          "sha1": "4482b225533b3f61ec0048b78b77c168c580977a",
          "md5": "5deba07ea8ae7db852876b1f24f32696"
        }
      ]
    },
    {
      "name": "runtimeElements",
      "attributes": {
        "org.gradle.category": "library",
        "org.gradle.dependency.bundling": "external",
        "org.gradle.jvm.version": 21,
        "org.gradle.libraryelements": "jar",
        "org.gradle.usage": "java-runtime"
      },
      "dependencies": [
        {
          "group": "org.jetbrains",
          "module": "annotations",
          "version": {
            "requires": "26.0.1"
          }
        },
        {
          "group": "com.google.cloud",
          "module": "libraries-bom",
          "version": {
            "requires": "26.49.0"
          },
          "attributes": {
            "org.gradle.category": "platform"
          },
          "endorseStrictVersions": true
        },
        {
          "group": "com.google.code.gson",
          "module": "gson",
          "version": {
            "requires": "2.11.0"
          }
        },
        {
          "group": "org.slf4j",
          "module": "slf4j-api",
          "version": {
            "requires": "2.0.16"
          }
        },
        {
          "group": "commons-io",
          "module": "commons-io",
          "version": {
            "requires": "2.17.0"
          }
        },
        {
          "group": "org.apache.commons",
          "module": "commons-lang3",
          "version": {
            "requires": "3.17.0"
          }
        },
        {
          "group": "org.apache.commons",
          "module": "commons-exec",
          "version": {
            "requires": "1.4.0"
          }
        },
        {
          "group": "org.owasp.encoder",
          "module": "encoder",
          "version": {
            "requires": "1.3.1"
          }
        },
        {
          "group": "com.google.cloud",
          "module": "google-cloud-texttospeech",
          "version": {
            "requires": "2.53.0"
          }
        },
        {
          "group": "com.github.spotbugs",
          "module": "spotbugs-annotations",
          "version": {
            "requires": "4.8.6"
          }
        }
      ],
      "files": [
        {
          "name": "ffmpeg-java-id-1.2.9-beta2.4.jar",
          "url": "ffmpeg-java-id-1.2.9-beta2.4.jar",
          "size": 187450,
          "sha512": "9f20856a0b408743741ef346898f9fe1c57710e4c2dfc8d628aa3f897617ce38b31263e119841ae593259c6c6a9b2f099f38e8845e33c830b92f5a0b5e415d83",
          "sha256": "bb6d6224e115f19efbd47dd8ce7b3f99c6871a388218926cf1982021e53a7625",
          "sha1": "4482b225533b3f61ec0048b78b77c168c580977a",
          "md5": "5deba07ea8ae7db852876b1f24f32696"
        }
      ]
    },
    {
      "name": "javadocElements",
      "attributes": {
        "org.gradle.category": "documentation",
        "org.gradle.dependency.bundling": "external",
        "org.gradle.docstype": "javadoc",
        "org.gradle.usage": "java-runtime"
      },
      "files": [
        {
          "name": "ffmpeg-java-id-1.2.9-beta2.4-javadoc.jar",
          "url": "ffmpeg-java-id-1.2.9-beta2.4-javadoc.jar",
          "size": 4619594,
          "sha512": "08bc8ecb7ef3cb0860e12fa47c562f1d678409137dae664663d85b45d5023a77fbcfb4b858839d6ec88251458553512b1594b35e828cb1215fe6420fc141e606",
          "sha256": "94bf7eaad7c858d967c493c9497a17ddf5a29cbfae53c81db33c71db822fa7e0",
          "sha1": "35c16a39318533f69cf135947824355972912a5f",
          "md5": "5c57a5aeaedb72e674927a04cb2a6ef2"
        }
      ]
    },
    {
      "name": "sourcesElements",
      "attributes": {
        "org.gradle.category": "documentation",
        "org.gradle.dependency.bundling": "external",
        "org.gradle.docstype": "sources",
        "org.gradle.usage": "java-runtime"
      },
      "files": [
        {
          "name": "ffmpeg-java-id-1.2.9-beta2.4-sources.jar",
          "url": "ffmpeg-java-id-1.2.9-beta2.4-sources.jar",
          "size": 132968,
          "sha512": "e5543228d0d1d33a709d6473f9a15254104d7ab07236242a9f317cdede6c6b7a52a080dad91ae3f038b4c30ef851548ef4ea528ff52f5fd40c5b6ee78281df57",
          "sha256": "6041a9a058079c7810c4e9b1467259434071d928801cdfb5020977945f407768",
          "sha1": "4e450ee541cac38ef985a8bf9bc1b0e60d89980a",
          "md5": "9c68fe95136e54137c910d8aa1ed1199"
        }
      ]
    }
  ]
}
